pipeline_sdk_test72/__init__.py
pipeline_sdk_test72/auth_service.py
pipeline_sdk_test72/inference_pipeline.py
pipeline_sdk_test72/model_inference_dsl_component.py
pipeline_sdk_test72/model_train_dsl_component.py
pipeline_sdk_test72/model_validate_dsl_component.py
pipeline_sdk_test72/pipeline_util.py
pipeline_sdk_test72/run_inference_pipeline.py
pipeline_sdk_test72/run_training_pipeline.py
pipeline_sdk_test72/run_validate_pipeline.py
pipeline_sdk_test72/train_pipeline.py
pipeline_sdk_test72/validate_pipeline.py
pipeline_sdk_test72-1.0.0.dist-info/METADATA
pipeline_sdk_test72-1.0.0.dist-info/WHEEL
pipeline_sdk_test72-1.0.0.dist-info/top_level.txt
pipeline_sdk_test72-1.0.0.dist-info/RECORD
